{
  "abbreviation": "AZ",
  "metadata": {
    "source": "https://taxfoundation.org/...",
    "last_verified": "2025-12-15",
    "verified_by": "manual"
  },
  "salesTax": {
    "stateRate": 0.056,
    "metadata": {
      "source": "https://taxfoundation.org/...",
      "last_verified": "2025-12-15",
      "verified_by": "manual"
    },
    "averageLocalRate": 0.028,
    "combinedRate": 0.084,
    "categories": {
      "groceries": {
        "taxable": false,
        "rate": 0
      },
      "preparedFood": {
        "taxable": true,
        "rate": 0.084
      },
      "utilities": {
        "taxable": true,
        "rate": 0.084
      },
      "services": {
        "taxable": false,
        "rate": 0
      },
      "digitalGoods": {
        "taxable": true,
        "rate": 0.084
      },
      "medicine": {
        "taxable": false,
        "rate": 0.056
      },
      "streamingSubscriptions": {
        "taxable": true,
        "rate": 0.084
      }
    }
  },
  "propertyTax": {
    "averageEffectiveRate": 0.6,
    "metadata": {
      "source": "https://taxfoundation.org/...",
      "last_verified": "2025-12-15",
      "verified_by": "manual"
    },
    "hasPropertyTax": true,
    "lastUpdated": "2025-05-19T14:29:16.723Z"
  },
  "retirementIncome": {
    "socialSecurityTaxed": false,
    "metadata": {
      "source": "https://taxfoundation.org/...",
      "last_verified": "2025-12-15",
      "verified_by": "manual"
    },
    "pensionsTaxed": false,
    "iraDistributionsTaxed": false,
    "retirementIncomeExemption": 0,
    "retirementIncomeExemptionAgeRequirement": 0
  },
  "vehicleTax": {
    "rate": 0,
    "metadata": {
      "source": "https://taxfoundation.org/...",
      "last_verified": "2025-12-15",
      "verified_by": "manual"
    },
    "hasRelief": false,
    "isCountyBased": false,
    "specialAssessmentRules": ""
  },
  "costOfLivingIndex": 100,
    "costOfLivingIndexMetadata": {
      "source": "https://taxfoundation.org/...",
      "last_verified": "2025-12-15",
      "verified_by": "manual"
    },
  "lifestyleTags": [],
  "incomeTax": {
    "metadata": {
      "source": "https://taxfoundation.org/...",
      "last_verified": "2025-12-15",
      "verified_by": "manual"
    },
    "brackets": {
      "single": [
        {
          "min": 0,
          "max": null,
          "rate": 2.5
        }
      ],
      "married": [
        {
          "min": 0,
          "max": null,
          "rate": 2.5
        }
      ],
      "headOfHousehold": [
        {
          "min": 0,
          "max": null,
          "rate": 2.5
        }
      ],
      "marriedSeparate": [
        {
          "min": 0,
          "max": null,
          "rate": 2.5
        }
      ]
    },
    "hasIncomeTax": true,
    "personalExemption": 0,
        "personalExemptionMetadata": {
          "source": "https://taxfoundation.org/...",
          "last_verified": "2025-12-15",
          "verified_by": "manual"
        },
    "dependentExemption": 0,
        "dependentExemptionMetadata": {
          "source": "https://taxfoundation.org/...",
          "last_verified": "2025-12-15",
          "verified_by": "manual"
        },
    "standardDeduction": {
          "standardDeductionMetadata": {
            "source": "https://taxfoundation.org/...",
            "last_verified": "2025-12-15",
            "verified_by": "manual"
          },
      "married": 30000,
      "marriedSeparate": 15000,
      "single": 15000,
      "headOfHousehold": 22500
    },
    "taxCredits": {
          "taxCreditsMetadata": {
            "source": "https://taxfoundation.org/...",
            "last_verified": "2025-12-15",
            "verified_by": "manual"
          },
      "childTaxCredit": 0,
      "childCareTaxCredit": 0,
      "earnedIncomeTaxCredit": false
    }
  }
}