{
  "abbreviation": "SD",
  "salesTax": {
    "stateRate": 0.042,
    "averageLocalRate": 0.019,
    "combinedRate": 0.061,
    "categories": {
      "groceries": {
        "taxable": true,
        "rate": 0.045
      },
      "preparedFood": {
        "taxable": true,
        "rate": 0.064
      },
      "utilities": {
        "taxable": true,
        "rate": 0.064
      },
      "services": {
        "taxable": true,
        "rate": 0.064
      },
      "digitalGoods": {
        "taxable": true,
        "rate": 0.064
      },
      "medicine": {
        "taxable": false,
        "rate": 0.042
      },
      "streamingSubscriptions": {
        "taxable": true,
        "rate": 0.064
      }
    }
  },
  "propertyTax": {
    "averageEffectiveRate": 1.01,
    "hasPropertyTax": true,
    "lastUpdated": "2025-05-19T14:29:16.723Z"
  },
  "retirementIncome": {
    "socialSecurityTaxed": false,
    "pensionsTaxed": false,
    "iraDistributionsTaxed": false,
    "retirementIncomeExemption": 0,
    "retirementIncomeExemptionAgeRequirement": 0
  },
  "vehicleTax": {
    "rate": 0,
    "hasRelief": false,
    "isCountyBased": false,
    "specialAssessmentRules": ""
  },
  "costOfLivingIndex": 100,
  "lifestyleTags": [],
  "incomeTax": {
    "brackets": {
      "single": [
        {
          "min": 0,
          "max": null,
          "rate": 0
        }
      ],
      "married": [
        {
          "min": 0,
          "max": null,
          "rate": 0
        }
      ],
      "headOfHousehold": [
        {
          "min": 0,
          "max": null,
          "rate": 0
        }
      ],
      "marriedSeparate": [
        {
          "min": 0,
          "max": null,
          "rate": 0
        }
      ]
    },
    "hasIncomeTax": true,
    "personalExemption": 0,
    "dependentExemption": 0,
    "standardDeduction": {
      "single": 0,
      "marriedSeparate": 0,
      "married": 0,
      "headOfHousehold": 0
    },
    "taxCredits": {
      "childTaxCredit": 0,
      "childCareTaxCredit": 0,
      "earnedIncomeTaxCredit": false
    }
  }
}